Workbook

Sheet Snitch_Fashion_Sales_cleaned
A1: Order_ID | B1: Customer_Name | C1: Product_Category | D1: Product_Name | E1: Units_Sold | F1: Unit_Price | G1: Discount_% | H1: Sales_Amount | I1: Order_Date | J1: City | K1: Segment | L1: Net_Revenue | M1: Profit | N1: City_Key | O1: Product_Key | P1: Date_Key
A2: 1000 | B2: Brian Thompson | C2: Jeans | D2: Slim Fit Jeans | E2: 4 | F2: 842 | G2: 0.6 | H2: =E2*F2 -> 3368 | I2: 45715 | J2: Delhi | K2: B2C | L2: =H2*(1-G2) -> 1347.2 | M2: 336.8 | N2: =_xlfn.XLOOKUP(Snitch_Fashion_Sales_cleaned!$J2,Table2[City],Table2[City_Key],"not found") -> 1 | O2: =_xlfn.XLOOKUP(Snitch_Fashion_Sales_cleaned!$D2,Table4[Product_Name],Table4[Product_Key],"not found") -> 1 | P2: =_xlfn.XLOOKUP(Snitch_Fashion_Sales_cleaned!$I2,Table3[Order_Date],Table3[Date_Key]) -> 1
A3: 1001 | B3: Shaun Ross | C3: Jeans | D3: Slim Fit Jeans | E3: 1 | F3: 2366.615 | G3: 0.51 | H3: =E3*F3 -> 2366.615 | I3: 45853 | J3: Ahmedabad | K3: B2B | L3: =H3*(1-G3) -> 1159.6413 | M3: 289.91034 | N3: =_xlfn.XLOOKUP(Snitch_Fashion_Sales_cleaned!$J3,Table2[City],Table2[City_Key],"not found") -> 2 | O3: =_xlfn.XLOOKUP(Snitch_Fashion_Sales_cleaned!$D3,Table4[Product_Name],Table4[Product_Key],"not found") -> 1 | P3: =_xlfn.XLOOKUP(Snitch_Fashion_Sales_cleaned!$I3,Table3[Order_Date],Table3[Date_Key]) -> 2
A4: 1002 | B4: Sarah Snyder | C4: Jackets | D4: Puffer Coat | E4: 1 | F4: 637.82 | G4: 0.51 | H4: =E4*F4 -> 637.82 | I4: 45659 | J4: Mumbai | K4: B2B | L4: =H4*(1-G4) -> 312.5318 | M4: -158.03 | N4: =_xlfn.XLOOKUP(Snitch_Fashion_Sales_cleaned!$J4,Table2[City],Table2[City_Key],"not found") -> 3 | O4: =_xlfn.XLOOKUP(Snitch_Fashion_Sales_cleaned!$D4,Table4[Product_Name],Table4[Product_Key],"not found") -> 2 | P4: =_xlfn.XLOOKUP(Snitch_Fashion_Sales_cleaned!$I4,Table3[Order_Date],Table3[Date_Key]) -> 3
A5: 1003 | B5: Jay Briggs | C5: Shoes | D5: Loafers | E5: 2 | F5: 2962.27 | G5: 0.51 | H5: =E5*F5 -> 5924.54 | I5: 45826 | J5: Bangalore | K5: B2B | L5: =H5*(1-G5) -> 2903.0246 | M5: 2296.5 | N5: =_xlfn.XLOOKUP(Snitch_Fashion_Sales_cleaned!$J5,Table2[City],Table2[City_Key],"not found") -> 4 | O5: =_xlfn.XLOOKUP(Snitch_Fashion_Sales_cleaned!$D5,Table4[Product_Name],Table4[Product_Key],"not found") -> 3 | P5: =_xlfn.XLOOKUP(Snitch_Fashion_Sales_cleaned!$I5,Table3[Order_Date],Table3[Date_Key]) -> 4
A6: 1004 | B6: Maria Blake | C6: Accessories | D6: Belts | E6: 1 | F6: 2881.07 | G6: 0.27 | H6: =E6*F6 -> 2881.07 | I6: 45647 | J6: Hyderabad | K6: B2B | L6: =H6*(1-G6) -> 2103.1811 | M6: 63.66 | N6: =_xlfn.XLOOKUP(Snitch_Fashion_Sales_cleaned!$J6,Table2[City],Table2[City_Key],"not found") -> 5 | O6: =_xlfn.XLOOKUP(Snitch_Fashion_Sales_cleaned!$D6,Table4[Product_Name],Table4[Product_Key],"not found") -> 4 | P6: =_xlfn.XLOOKUP(Snitch_Fashion_Sales_cleaned!$I6,Table3[Order_Date],Table3[Date_Key]) -> 5
A7: 1005 | B7: Samuel Miller | C7: T-Shirts | D7: Crop Top | E7: 4 | F7: 2001.55 | G7: 0.51 | H7: =E7*F7 -> 8006.2 | I7: 45265 | J7: Mumbai | K7: B2B | L7: =H7*(1-G7) -> 3923.038 | M7: 1477.73 | N7: =_xlfn.XLOOKUP(Snitch_Fashion_Sales_cleaned!$J7,Table2[City],Table2[City_Key],"not found") -> 3 | O7: =_xlfn.XLOOKUP(Snitch_Fashion_Sales_cleaned!$D7,Table4[Product_Name],Table4[Product_Key],"not found") -> 5 | P7: =_xlfn.XLOOKUP(Snitch_Fashion_Sales_cleaned!$I7,Table3[Order_Date],Table3[Date_Key]) -> 6
A8: 1006 | B8: John Mclean | C8: Jeans | D8: Boyfriend Jeans | E8: 1 | F8: 2060.85 | G8: 0.51 | H8: =E8*F8 -> 2060.85 | I8: 45384 | J8: Ahmedabad | K8: B2B | L8: =H8*(1-G8) -> 1009.8165 | M8: 198.36 | N8: =_xlfn.XLOOKUP(Snitch_Fashion_Sales_cleaned!$J8,Table2[City],Table2[City_Key],"not found") -> 2 | O8: =_xlfn.XLOOKUP(Snitch_Fashion_Sales_cleaned!$D8,Table4[Product_Name],Table4[Product_Key],"not found") -> 6 | P8: =_xlfn.XLOOKUP(Snitch_Fashion_Sales_cleaned!$I8,Table3[Order_Date],Table3[Date_Key]) -> 7
A9: 1007 | B9: Dr. Kathryn Bass PhD | C9: Dresses | D9: Casual Midi | E9: 4 | F9: 3669.56 | G9: 0.51 | H9: =E9*F9 -> 14678.24 | I9: 45647 | J9: Bangalore | K9: B2C | L9: =H9*(1-G9) -> 7192.3376 | M9: 2490.01 | N9: =_xlfn.XLOOKUP(Snitch_Fashion_Sales_cleaned!$J9,Table2[City],Table2[City_Key],"not found") -> 4 | O9: =_xlfn.XLOOKUP(Snitch_Fashion_Sales_cleaned!$D9,Table4[Product_Name],Table4[Product_Key],"not found") -> 7 | P9: =_xlfn.XLOOKUP(Snitch_Fashion_Sales_cleaned!$I9,Table3[Order_Date],Table3[Date_Key]) -> 5
A10: 1008 | B10: Marie Fisher | C10: Accessories | D10: Sunglasses | E10: 3 | F10: 2577.635 | G10: 0.51 | H10: =E10*F10 -> 7732.905 | I10: 45647 | J10: Ahmedabad | K10: B2C | L10: =H10*(1-G10) -> 3789.1235 | M10: -886.8 | N10: =_xlfn.XLOOKUP(Snitch_Fashion_Sales_cleaned!$J10,Table2[City],Table2[City_Key],"not found") -> 2 | O10: =_xlfn.XLOOKUP(Snitch_Fashion_Sales_cleaned!$D10,Table4[Product_Name],Table4[Product_Key],"not found") -> 8 | P10: =_xlfn.XLOOKUP(Snitch_Fashion_Sales_cleaned!$I10,Table3[Order_Date],Table3[Date_Key]) -> 5
A11: 1009 | B11: Dale Perry | C11: T-Shirts | D11: Oversized T-shirt | E11: 5 | F11: 3027.66 | G11: 0.51 | H11: =E11*F11 -> 15138.3 | I11: 45858 | J11: Bangalore | K11: B2B | L11: =H11*(1-G11) -> 7417.767 | M11: -972.73 | N11: =_xlfn.XLOOKUP(Snitch_Fashion_Sales_cleaned!$J11,Table2[City],Table2[City_Key],"not found") -> 4 | O11: =_xlfn.XLOOKUP(Snitch_Fashion_Sales_cleaned!$D11,Table4[Product_Name],Table4[Product_Key],"not found") -> 9 | P11: =_xlfn.XLOOKUP(Snitch_Fashion_Sales_cleaned!$I11,Table3[Order_Date],Table3[Date_Key]) -> 8
A12: 1010 | B12: Oscar Turner | C12: T-Shirts | D12: Crop Top | E12: 4 | F12: 4007.02 | G12: 0.51 | H12: =E12*F12 -> 16028.08 | I12: 45647 | J12: Pune | K12: B2B | L12: =H12*(1-G12) -> 7853.7592 | M12: -950.38 | N12: =_xlfn.XLOOKUP(Snitch_Fashion_Sales_cleaned!$J12,Table2[City],Table2[City_Key],"not found") -> 6 | O12: =_xlfn.XLOOKUP(Snitch_Fashion_Sales_cleaned!$D12,Table4[Product_Name],Table4[Product_Key],"not found") -> 5 | P12: =_xlfn.XLOOKUP(Snitch_Fashion_Sales_cleaned!$I12,Table3[Order_Date],Table3[Date_Key]) -> 5
A13: 1011 | B13: Jacob Sanchez | C13: Accessories | D13: Belts | E13: 3 | F13: 2515.415 | G13: 0.51 | H13: =E13*F13 -> 7546.245 | I13: 45804 | J13: Delhi | K13: B2C | L13: =H13*(1-G13) -> 3697.66 | M13: 1370.67 | N13: =_xlfn.XLOOKUP(Snitch_Fashion_Sales_cleaned!$J13,Table2[City],Table2[City_Key],"not found") -> 1 | O13: =_xlfn.XLOOKUP(Snitch_Fashion_Sales_cleaned!$D13,Table4[Product_Name],Table4[Product_Key],"not found") -> 4 | P13: =_xlfn.XLOOKUP(Snitch_Fashion_Sales_cleaned!$I13,Table3[Order_Date],Table3[Date_Key]) -> 9
... A2501: 3499 | B2501: Zachary Werner | C2501: T-Shirts | D2501: Graphic Tee | E2501: 6 | F2501: 1239.75 | G2501: 0.51 | H2501: =E2501*F2501 -> 7438.5 | I2501: 45647 | J2501: Mumbai | K2501: B2C | L2501: =H2501*(1-G2501) -> 3644.865 | M2501: 715.15 | N2501: =_xlfn.XLOOKUP(Snitch_Fashion_Sales_cleaned!$J2501,Table2[City],Table2[City_Key],"not found") -> 3 | O2501: =_xlfn.XLOOKUP(Snitch_Fashion_Sales_cleaned!$D2501,Table4[Product_Name],Table4[Product_Key],"not found") -> 17 | P2501: =_xlfn.XLOOKUP(Snitch_Fashion_Sales_cleaned!$I2501,Table3[Order_Date],Table3[Date_Key]) -> 5

Sheet Dim_Product
A1: Product_Key | B1: Product_Category | C1: Product_Name
A2: 1 | B2: Jeans | C2: Slim Fit Jeans
A3: 2 | B3: Jackets | C3: Puffer Coat
A4: 3 | B4: Shoes | C4: Loafers
A5: 4 | B5: Accessories | C5: Belts
A6: 5 | B6: T-Shirts | C6: Crop Top
A7: 6 | B7: Jeans | C7: Boyfriend Jeans
A8: 7 | B8: Dresses | C8: Casual Midi
A9: 8 | B9: Accessories | C9: Sunglasses
A10: 9 | B10: T-Shirts | C10: Oversized T-shirt
A11: 10 | B11: Jeans | C11: Straight Cut
A12: 11 | B12: Shoes | C12: Sneakers
A13: 12 | B13: Dresses | C13: Maxi Dress
... A25: 24 | B25: Accessories | C25: Caps

Sheet Dim_Date
A1: Date_Key | B1: Order_Date | C1: Year | D1: Month | E1: Month_Number
A2: 1 | B2: 45715 | C2: =YEAR(B2) -> 2025 | D2: =TEXT(B2,"mmmm") -> February | E2: =MONTH(B2) -> 2
A3: 2 | B3: 45853 | C3: =YEAR(B3) -> 2025 | D3: =TEXT(B3,"mmmm") -> July | E3: =MONTH(B3) -> 7
A4: 3 | B4: 45659 | C4: =YEAR(B4) -> 2025 | D4: =TEXT(B4,"mmmm") -> January | E4: =MONTH(B4) -> 1
A5: 4 | B5: 45826 | C5: =YEAR(B5) -> 2025 | D5: =TEXT(B5,"mmmm") -> June | E5: =MONTH(B5) -> 6
A6: 5 | B6: 45647 | C6: =YEAR(B6) -> 2024 | D6: =TEXT(B6,"mmmm") -> December | E6: =MONTH(B6) -> 12
A7: 6 | B7: 45265 | C7: =YEAR(B7) -> 2023 | D7: =TEXT(B7,"mmmm") -> December | E7: =MONTH(B7) -> 12
A8: 7 | B8: 45384 | C8: =YEAR(B8) -> 2024 | D8: =TEXT(B8,"mmmm") -> April | E8: =MONTH(B8) -> 4
A9: 8 | B9: 45858 | C9: =YEAR(B9) -> 2025 | D9: =TEXT(B9,"mmmm") -> July | E9: =MONTH(B9) -> 7
A10: 9 | B10: 45804 | C10: =YEAR(B10) -> 2025 | D10: =TEXT(B10,"mmmm") -> May | E10: =MONTH(B10) -> 5
A11: 10 | B11: 45526 | C11: =YEAR(B11) -> 2024 | D11: =TEXT(B11,"mmmm") -> August | E11: =MONTH(B11) -> 8
A12: 11 | B12: 45556 | C12: =YEAR(B12) -> 2024 | D12: =TEXT(B12,"mmmm") -> September | E12: =MONTH(B12) -> 9
A13: 12 | B13: 45591 | C13: =YEAR(B13) -> 2024 | D13: =TEXT(B13,"mmmm") -> October | E13: =MONTH(B13) -> 10
... A563: 562 | B563: 45291 | C563: =YEAR(B563) -> 2023 | D563: =TEXT(B563,"mmmm") -> December | E563: =MONTH(B563) -> 12

Sheet Dim_City
A1: City_Key | B1: City
A2: 1 | B2: Delhi
A3: 2 | B3: Ahmedabad
A4: 3 | B4: Mumbai
A5: 4 | B5: Bangalore
A6: 5 | B6: Hyderabad
A7: 6 | B7: Pune

Sheet pivot table
A2: sales by product category | H2: sales by city | K2: product performance | S2: monthly sales
A3: Product Category | B3: Sum of Sales_Amount | H3: City | I3: Sum of Sales_Amount | K3: Product Name | L3: Sum of Units_Sold | M3: Sum of Sales_Amount | N3: Sum of Profit | S3: Month | T3: Sum of Sales_Amount
A4: Accessories | B4: 3674352.5 | H4: Ahmedabad | I4: 4108722.7 | K4: Belts | L4: 333 | M4: 865556.51 | N4: 99400.515 | S4: Jan | T4: 1571155.6
A5: Dresses | B5: 4358228.5 | H5: Bengaluru | I5: 3950732.6 | K5: Bodycon | L5: 360 | M5: 1012077.4 | N5: 75796.038 | S5: Feb | T5: 1307362.2
A6: Jackets | B6: 3679354.5 | H6: Delhi | I6: 4000698.9 | K6: Bomber Jacket | L6: 315 | M6: 738390.54 | N6: 87550.402 | S6: Mar | T6: 1596373.6
A7: Jeans | B7: 4306706.5 | H7: Hyderabad | I7: 4176862.1 | K7: Boots | L7: 354 | M7: 887371.53 | N7: 76385.57 | S7: Apr | T7: 1385711.1
A8: Shoes | B8: 4009980.7 | H8: Mumbai | I8: 4210434.1 | K8: Boyfriend Jeans | L8: 326 | M8: 968388.34 | N8: 85882.757 | S8: May | T8: 1704209.2
A9: T-Shirts | B9: 3997875.7 | H9: Pune | I9: 3579048 | K9: Caps | L9: 301.5 | M9: 725882.33 | N9: 63849.684 | S9: Jun | T9: 1365937.2
A10: Grand Total | B10: 24026498 | H10: Grand Total | I10: 24026498 | K10: Casual Midi | L10: 430 | M10: 1293809 | N10: 87332.112 | S10: Jul | T10: 1579181.9
K11: Classic Tee | L11: 434 | M11: 1177808.8 | N11: 90683.398 | S11: Aug | T11: 1637107.5
A12: profit by product category | H12: sales by segment | K12: Crop Top | L12: 386 | M12: 868607.38 | N12: 88362.138 | S12: Sep | T12: 1484767.4
A13: Product Category | B13: Sum of Profit | H13: Segment | I13: Sum of Sales_Amount | K13: Denim Jacket | L13: 297 | M13: 797045.53 | N13: 71025.777 | S13: Oct | T13: 1432760.2
A14: Accessories | B14: 334161.97 | H14: B2B | I14: 16136211 | K14: Graphic Tee | L14: 420 | M14: 1122212.4 | N14: 81809.133 | S14: Nov | T14: 1359757.4
A15: Dresses | B15: 380932.37 | H15: B2C | I15: 7890287.8 | K15: Leather Jacket | L15: 346 | M15: 939078.22 | N15: 78328.586 | S15: Dec | T15: 7602175.2
A16: Jackets | B16: 318303.01 | H16: Grand Total | I16: 24026498 | K16: Loafers | L16: 359 | M16: 1049599.5 | N16: 95768.556 | S16: Grand Total | T16: 24026498
A17: Jeans | B17: 341391.12 | K17: Maxi Dress | L17: 355 | M17: 972842.8 | N17: 105932.89
A18: Shoes | B18: 323840.64 | K18: Oversized T-shirt | L18: 288 | M18: 829247.12 | N18: 72998.466
A19: T-Shirts | B19: 333853.14 | K19: Puffer Coat | L19: 454 | M19: 1204840.2 | N19: 81398.241
A20: Grand Total | B20: 2032482.2 | K20: Ripped Denim | L20: 470 | M20: 1262074.2 | N20: 85695.888
K21: Slim Fit Jeans | L21: 356 | M21: 838796.77 | N21: 73941.752
K22: Slip-ons | L22: 388 | M22: 999837.53 | N22: 63284.337
K23: Sneakers | L23: 415 | M23: 1073172.1 | N23: 88402.173
K24: Straight Cut | L24: 436 | M24: 1237447.2 | N24: 95870.721
K25: Sunglasses | L25: 325 | M25: 842303.62 | N25: 62313.409
K26: Watches | L26: 438 | M26: 1240610.1 | N26: 108598.36
K27: Wrap Dress | L27: 385 | M27: 1079499.3 | N27: 111871.33
K28: Grand Total | L28: 8971.5 | M28: 24026498 | N28: 2032482.2
